ReactZhongwenWendang/README.md
ReactZhongwenWendang/__init__.py
ReactZhongwenWendang/__main__.py
ReactZhongwenWendang/file.epub
ReactZhongwenWendang/index.html
ReactZhongwenWendang/css/__init__.py
ReactZhongwenWendang/css/annotations.css
ReactZhongwenWendang/css/main.css
ReactZhongwenWendang/css/normalize.css
ReactZhongwenWendang/css/popup.css
ReactZhongwenWendang/font/__init__.py
ReactZhongwenWendang/font/fontello.eot
ReactZhongwenWendang/font/fontello.svg
ReactZhongwenWendang/font/fontello.ttf
ReactZhongwenWendang/font/fontello.woff
ReactZhongwenWendang/img/__init__.py
ReactZhongwenWendang/img/annotator-glyph-sprite.png
ReactZhongwenWendang/img/annotator-icon-sprite.png
ReactZhongwenWendang/img/apple-touch-icon.png
ReactZhongwenWendang/img/cancelfullscreen.png
ReactZhongwenWendang/img/close.png
ReactZhongwenWendang/img/fullscreen.png
ReactZhongwenWendang/img/loader.gif
ReactZhongwenWendang/img/menu-icon.png
ReactZhongwenWendang/img/save.png
ReactZhongwenWendang/img/saved.png
ReactZhongwenWendang/img/settings-s.png
ReactZhongwenWendang/img/settings.png
ReactZhongwenWendang/img/star.png
ReactZhongwenWendang/js/__init__.py
ReactZhongwenWendang/js/epub.js
ReactZhongwenWendang/js/epub.min.js
ReactZhongwenWendang/js/epub.min.map
ReactZhongwenWendang/js/hooks.min.js
ReactZhongwenWendang/js/hooks.min.map
ReactZhongwenWendang/js/reader.js
ReactZhongwenWendang/js/reader.js.map
ReactZhongwenWendang/js/reader.min.js
ReactZhongwenWendang/js/reader.min.map
ReactZhongwenWendang/js/hooks/__init__.py
ReactZhongwenWendang/js/hooks/extensions/__init__.py
ReactZhongwenWendang/js/hooks/extensions/highlight.js
ReactZhongwenWendang/js/libs/__init__.py
ReactZhongwenWendang/js/libs/jquery.min.js
ReactZhongwenWendang/js/libs/localforage.min.js
ReactZhongwenWendang/js/libs/screenfull.js
ReactZhongwenWendang/js/libs/screenfull.min.js
ReactZhongwenWendang/js/libs/zip.min.js
ReactZhongwenWendang/js/plugins/__init__.py
ReactZhongwenWendang/js/plugins/hypothesis.js
react_zhongwen_wendang-2024.3.1.0.dist-info/METADATA
react_zhongwen_wendang-2024.3.1.0.dist-info/WHEEL
react_zhongwen_wendang-2024.3.1.0.dist-info/entry_points.txt
react_zhongwen_wendang-2024.3.1.0.dist-info/top_level.txt
react_zhongwen_wendang-2024.3.1.0.dist-info/RECORD
